dummy.pypy38-pp73-x86_64-linux-gnu.so
redislite/__init__.py
redislite/client.py
redislite/configuration.py
redislite/debug.py
redislite/package_metadata.json
redislite/patch.py
redislite/bin/redis-cli
redislite/bin/redis-server
redislite-6.2.899109.data/scripts/redis-cli
redislite-6.2.899109.data/scripts/redis-server
redislite-6.2.899109.dist-info/LICENSE.txt
redislite-6.2.899109.dist-info/METADATA
redislite-6.2.899109.dist-info/WHEEL
redislite-6.2.899109.dist-info/top_level.txt
redislite-6.2.899109.dist-info/RECORD
