Metadata-Version: 2.1
Name: redislite
Version: 6.2.899109
Summary: Redis built into a python package
Home-page: https://github.com/yahoo/redislite
Author: Verizon Media Python Platform Team
Author-email: 254983+dwighthubbard@users.noreply.github.com
License: BSD License
Project-URL: CI Pipeline, https://cd.screwdriver.cd/pipelines/2880/events
Project-URL: Documentation, https://redislite.readthedocs.io/en/latest/
Project-URL: Source, https://github.com/yahoo/redislite
Keywords: redis sqlite python service integrated
Classifier: Development Status :: 5 - Production/Stable
Classifier: Environment :: Console
Classifier: Intended Audience :: Developers
Classifier: License :: OSI Approved :: BSD License
Classifier: Operating System :: MacOS :: MacOS X
Classifier: Operating System :: POSIX :: BSD :: FreeBSD
Classifier: Operating System :: POSIX :: Linux
Classifier: Operating System :: POSIX :: SunOS/Solaris
Classifier: Operating System :: POSIX
Classifier: Programming Language :: C
Classifier: Programming Language :: Python :: 3
Classifier: Programming Language :: Python :: 3.8
Classifier: Programming Language :: Python :: 3.9
Classifier: Programming Language :: Python :: 3.10
Classifier: Programming Language :: Python :: 3.11
Classifier: Programming Language :: Python :: Implementation :: CPython
Classifier: Programming Language :: Python
Classifier: Topic :: Software Development :: Libraries :: Python Modules
Classifier: Topic :: Software Development :: Libraries
Classifier: Topic :: System :: Systems Administration
Classifier: Topic :: Utilities
Requires-Python: >=3.8.0
License-File: LICENSE.txt
Requires-Dist: redis >=4.5
Requires-Dist: psutil
Requires-Dist: setuptools >38.0
